<?xml version="1.0" encoding="UTF-8"?>
<openerp>
    <data>

        <record model="ir.ui.view" id="view_event_form">
            <field name="name">Add seance</field>
            <field name="model">event.event</field>
            <field name="inherit_id" ref="event.view_event_form"/>
            <field name="arch" type="xml">
                <xpath expr="//notebook">
                    <page string="Seances" name="seances">
                        <field name="seance_ids"/>
                    </page>
                </xpath>
            </field>
        </record>

        

    </data>
</openerp>
